<?xml version="1.0" encoding="utf-8" ?>
<Defs>

	<BiomeDef>
		<defName>Talyxian_Wasteland</defName>
		<label>talyxian Forest</label>
		<description>A strange and dangerous forest filled with life, with clearings of small deserts. The "plants" of this biome are actually sessile animals. </description>
		<implemented>true</implemented>
		<workerClass>VilousTal.BiomeWorker_Talyxian</workerClass>
		<animalDensity>3.7</animalDensity>
		<plantDensity>0.8</plantDensity>
		<settlementSelectionWeight>1</settlementSelectionWeight>
		<movementDifficulty>1</movementDifficulty>
		<texture>World/Biomes/TalyxianBiome</texture>
		<forageability>1</forageability>
		<foragedFood>RawBerries</foragedFood>
		<wildPlantRegrowDays>20</wildPlantRegrowDays>
		<soundsAmbient>
			<li>Ambient_NightInsects_Standard</li>
		</soundsAmbient>
		<diseaseMtbDays>50</diseaseMtbDays>
		<diseases>
			<li>
				<diseaseInc>Disease_Flu</diseaseInc>
				<commonality>100</commonality>
			</li>
			<li>
				<diseaseInc>Disease_Plague</diseaseInc>
				<commonality>100</commonality>
			</li>
			<li>
				<diseaseInc>Disease_Malaria</diseaseInc>
				<commonality>100</commonality>
			</li>
			<li>
				<diseaseInc>Disease_GutWorms</diseaseInc>
				<commonality>50</commonality>
			</li>
			<li>
				<diseaseInc>Disease_FibrousMechanites</diseaseInc>
				<commonality>30</commonality>
			</li>
			<li>
				<diseaseInc>Disease_SensoryMechanites</diseaseInc>
				<commonality>30</commonality>
			</li>
			<li>
				<diseaseInc>Disease_MuscleParasites</diseaseInc>
				<commonality>50</commonality>
			</li>

			<li>
				<diseaseInc>Disease_AnimalFlu</diseaseInc>
				<commonality>100</commonality>
			</li>
			<li>
				<diseaseInc>Disease_AnimalPlague</diseaseInc>
				<commonality>100</commonality>
			</li>
		</diseases>
		<terrainsByFertility>
			<li>
				<terrain>Sand</terrain>
				<min>-999</min>
				<max>0.15</max>
			</li>
			<li>
				<terrain>TalyxianSoil</terrain>
				<min>0.15</min>
				<max>0.87</max>
			</li>
			<li>
				<terrain>Soil</terrain>
				<min>0.87</min>
				<max>999</max>
			</li>
		</terrainsByFertility>
		<terrainPatchMakers>
			<li>
				<perlinFrequency>0.015</perlinFrequency>
				<thresholds>
					<li>
						<terrain>WaterShallow</terrain>
						<min>0.93</min>
						<max>1.06</max>
					</li>
				</thresholds>
			</li>
		</terrainPatchMakers>
		<baseWeatherCommonalities>
			<Clear>18</Clear>
			<Fog>1</Fog>
			<Rain>2</Rain>
			<DryThunderstorm>1</DryThunderstorm>
			<RainyThunderstorm>1</RainyThunderstorm>
			<FoggyRain>1</FoggyRain>
		</baseWeatherCommonalities>
		<wildPlants>
			<Plant_Grass>5.0</Plant_Grass>
			<TalGrass>5.0</TalGrass>
			<TalCattail>2.0</TalCattail>
			<TalMozuuk>0.5</TalMozuuk>
			<TreeHoncystis>0.5</TreeHoncystis>
			<TreeOysterbirch>0.25</TreeOysterbirch>
		</wildPlants>
		<wildAnimals>
			<SnailCow>0.1</SnailCow>
			<TalyxianGoat>0.9</TalyxianGoat>
			<TalyxianDog>0.15</TalyxianDog>
			<TalyxianStalker>0.1</TalyxianStalker>
			<UrchinCow>0.1</UrchinCow>
			<HouseMite>1.2</HouseMite>
			<Odei>1</Odei>
			<HandstandSnail>0.5</HandstandSnail>
			<TalyxianWolf>0.05</TalyxianWolf>
		</wildAnimals>
		<allowedPackAnimals>
			<li>UrchinCow</li>
			<li>SnailCow</li>
		</allowedPackAnimals>
	</BiomeDef>

</Defs>