<?xml version="1.0" encoding="utf-8"?>
<Defs>

  <SoundDef>
    <defName>Pawn_TalGoat_Call</defName>
    <context>MapOnly</context>
    <subSounds>
      <li>
        <grains>
          <li Class="AudioGrain_Folder">
            <clipFolderPath>Pawn/Animal/Talgoat/Calls</clipFolderPath>
          </li>
        </grains>
        <volumeRange>21~28</volumeRange>
        <pitchRange>0.7082353~1.114706</pitchRange>
        <distRange>0~50</distRange>
      </li>
    </subSounds>
  </SoundDef>
  <SoundDef>
    <defName>Pawn_TalGoat_Angry</defName>
    <context>MapOnly</context>
    <subSounds>
      <li>
        <grains>
          <li Class="AudioGrain_Clip">
            <clipPath>Pawn/Animal/Talgoat/Calls/Call2</clipPath>
          </li>
        </grains>
        <volumeRange>15~15</volumeRange>
        <pitchRange>0.9311765~1.091765</pitchRange>
        <distRange>0~50</distRange>
        <sustainLoop>False</sustainLoop>
      </li>
    </subSounds>
  </SoundDef>
  <SoundDef>
    <defName>Pawn_TalGoat_Death</defName>
    <context>MapOnly</context>
    <subSounds>
      <li>
        <grains>
          <li Class="AudioGrain_Clip">
            <clipPath>Pawn/Animal/Talgoat/Death</clipPath>
          </li>
        </grains>
        <volumeRange>18.04878~18.04878</volumeRange>
        <pitchRange>1.2~1.2</pitchRange>
        <distRange>0~50</distRange>
      </li>
    </subSounds>
  </SoundDef>
  <SoundDef>
    <defName>Pawn_TalGoat_Wounded</defName>
    <context>MapOnly</context>
    <subSounds>
      <li>
        <grains>
          <li Class="AudioGrain_Clip">
            <clipPath>Pawn/Animal/Talgoat/Pain</clipPath>
          </li>
        </grains>
        <volumeRange>13.5122~13.5122</volumeRange>
        <pitchRange>0.8~1</pitchRange>
        <distRange>0~50</distRange>
      </li>
    </subSounds>
  </SoundDef>
</Defs>
